flyingcloud/__init__.py
flyingcloud/base.py
flyingcloud/main.py
flyingcloud/utils/__init__.py
flyingcloud/utils/archive.py
flyingcloud/utils/file.py
flyingcloud/utils/importer.py
flyingcloud/utils/package_build.py
flyingcloud/utils/process.py
flyingcloud/utils/vcs.py
flyingcloud-0.3.1.data/scripts/flyingcloud
flyingcloud-0.3.1.dist-info/DESCRIPTION.rst
flyingcloud-0.3.1.dist-info/METADATA
flyingcloud-0.3.1.dist-info/metadata.json
flyingcloud-0.3.1.dist-info/RECORD
flyingcloud-0.3.1.dist-info/top_level.txt
flyingcloud-0.3.1.dist-info/WHEEL
