Metadata-Version: 2.0
Name: flyingcloud
Version: 0.3.1
Summary: Build Docker images using SaltStack
Home-page: https://github.com/cookbrite/flyingcloud
Author: MetaBrite, Inc.
Author-email: flyingcloud-admin@metabrite.com
License: Apache Software License 2.0
Keywords: docker saltstack devops automation
Platform: UNKNOWN
Classifier: Programming Language :: Python
Classifier: Programming Language :: Python :: 2.7
Classifier: Development Status :: 3 - Alpha
Classifier: Environment :: Console
Classifier: Intended Audience :: Developers
Classifier: Intended Audience :: Information Technology
Classifier: Intended Audience :: System Administrators
Classifier: License :: OSI Approved :: Apache Software License
Classifier: Operating System :: POSIX :: Linux
Classifier: Topic :: Utilities
Classifier: Topic :: System :: Clustering
Classifier: Topic :: System :: Distributed Computing
Requires-Dist: docker-py
Requires-Dist: psutil
Requires-Dist: pyyaml
Requires-Dist: requests
Requires-Dist: sh
Requires-Dist: six
